pyoculus_spec_fortran_module.cpython-38-darwin.so
pyoculus/__init__.py
pyoculus/integrators/__init__.py
pyoculus/integrators/base_integrator.py
pyoculus/integrators/rk_integrator.py
pyoculus/integrators/sdc_integrator.py
pyoculus/irrationals/__init__.py
pyoculus/irrationals/continued_fraction.py
pyoculus/problems/__init__.py
pyoculus/problems/base_problem.py
pyoculus/problems/spec_bfield.py
pyoculus/problems/spec_pjh.py
pyoculus/problems/spec_problem.py
pyoculus/problems/two_waves.py
pyoculus/solvers/__init__.py
pyoculus/solvers/base_solver.py
pyoculus/solvers/fixed_point.py
pyoculus/solvers/flux_surface_gr.py
pyoculus/solvers/lyapunov_exponent.py
pyoculus/solvers/manifolds.py
pyoculus/solvers/poincare_plot.py
pyoculus_spec_fortran_module.cpython-38-darwin.so.dSYM/Contents/Info.plist
pyoculus_spec_fortran_module.cpython-38-darwin.so.dSYM/Contents/Resources/DWARF/pyoculus_spec_fortran_module.cpython-38-darwin.so
pyoculus-0.1.3.dist-info/LICENSE
pyoculus-0.1.3.dist-info/METADATA
pyoculus-0.1.3.dist-info/WHEEL
pyoculus-0.1.3.dist-info/top_level.txt
pyoculus-0.1.3.dist-info/RECORD
