Metadata-Version: 2.1
Name: pyoculus
Version: 0.1.3
Summary: A Python version of Oculus - The eye into the chaos: a comprehensive magnetic field diagnostic package for non-integrable, toroidal magnetic fields
Home-page: https://github.com/zhisong/pyoculus
Author: Zhisong Qu, Arunav Kumar, Stuart Hudson
License: MIT
Platform: UNKNOWN
Classifier: Development Status :: 3 - Alpha
Classifier: License :: OSI Approved :: MIT License 
Classifier: Programming Language :: Python :: 3
Classifier: Topic :: Scientific/Engineering
Requires-Dist: numpy
Requires-Dist: scipy
Requires-Dist: importlib-metadata ; python_version < "3.8"
